{
	"name": "facttablegenpip",
	"properties": {
		"activities": [
			{
				"name": "facttablegen",
				"type": "ExecuteDataFlow",
				"dependsOn": [],
				"policy": {
					"timeout": "1.00:00:00",
					"retry": 0,
					"retryIntervalInSeconds": 30,
					"secureOutput": false,
					"secureInput": false
				},
				"userProperties": [],
				"typeProperties": {
					"dataflow": {
						"referenceName": "Facttablegen",
						"type": "DataFlowReference"
					},
					"staging": {
						"linkedService": {
							"referenceName": "AzureDataLakeStorage",
							"type": "LinkedServiceReference"
						},
						"folderPath": "stagingdata"
					},
					"compute": {
						"coreCount": 8,
						"computeType": "General"
					},
					"traceLevel": "Fine"
				}
			}
		],
		"annotations": [],
		"lastPublishTime": "2022-08-14T07:08:18Z"
	},
	"type": "Microsoft.DataFactory/factories/pipelines"
}